eswrap/LICENSE
eswrap/VERSION
eswrap/__init__.py
eswrap/main.py
eswrap/core/__init__.py
eswrap/core/es_handler/__init__.py
eswrap/core/es_handler/es_handler.py
eswrap/core/es_index/__init__.py
eswrap/core/es_index/es_index.py
eswrap/core/index_list/__init__.py
eswrap/core/index_list/index_list.py
eswrap/errors/__init__.py
eswrap/errors/indexes.py
eswrap/errors/queries.py
eswrap-0.5.2.dist-info/METADATA
eswrap-0.5.2.dist-info/WHEEL
eswrap-0.5.2.dist-info/top_level.txt
eswrap-0.5.2.dist-info/RECORD
