Metadata-Version: 2.1
Name: eswrap
Version: 0.5.2
Summary: Python wrapper for simple elasticsearch queries
Home-page: 
Author: Paul Tikken
Author-email: paul.tikken@gmail.com
License: GNU General Public License v3.0
Classifier: License :: OSI Approved :: GNU General Public License v3 or later (GPLv3+)
Classifier: Operating System :: POSIX :: Linux
Classifier: Programming Language :: Python
Classifier: Programming Language :: Python :: 3
Classifier: Programming Language :: Python :: 3.10
Requires-Python: >=3.10
Requires-Dist: elasticsearch >=8.10.0
